notehandler.py
distribute_setup.py
notehandler-0.6.dist-info/METADATA
notehandler-0.6.dist-info/top_level.txt
notehandler-0.6.dist-info/WHEEL
notehandler-0.6.dist-info/DESCRIPTION.rst
notehandler-0.6.dist-info/RECORD
notehandler-0.6.dist-info/pydist.json
notehandler-0.6.dist-info/entry_points.txt
notehandler-0.6.data/scripts/nh
